gole/__init__.py
gole/__main__.py
gole/app.py
gole/cache.py
gole/cli.py
gole/config.py
gole/dialogs/__init__.py
gole/dialogs/confirm.py
gole/dialogs/file_system.py
gole/gole.tcss
gole/locale/pt_BR/LC_MESSAGES/gole.mo
gole/locale/pt_BR/LC_MESSAGES/gole.po
gole/theme.py
gole/translation.py
gole/widgets/__init__.py
gole/widgets/board.py
gole/widgets/directory_tree.py
gole/widgets/settings.py
gole/widgets/text_area/__init__.py
gole/widgets/text_area/area.py
gole/widgets/text_area/binding.py
gole/widgets/text_area/history.py
gole/widgets/text_area/language.py
gole/widgets/text_area/pane.py
gole-1.0.2.post0.dist-info/METADATA
gole-1.0.2.post0.dist-info/WHEEL
gole-1.0.2.post0.dist-info/entry_points.txt
gole-1.0.2.post0.dist-info/licenses/LICENSE
gole-1.0.2.post0.dist-info/RECORD
