Metadata-Version: 2.4
Name: gole
Version: 1.0.2.post0
Summary: Terminal Text Editor
License: GNU GENERAL PUBLIC LICENSE
License-File: LICENSE
Keywords: tui,terminal,textual,cli,developer-tool
Author: taconi
Author-email: igor.taconi@protonmail.com
Requires-Python: ~=3.12
Classifier: Development Status :: 2 - Pre-Alpha
Classifier: Environment :: Console
Classifier: Intended Audience :: Developers
Classifier: License :: OSI Approved :: GNU General Public License v3 or later (GPLv3+)
Classifier: Programming Language :: Python :: 3.12
Classifier: Programming Language :: Python :: 3.13
Classifier: Programming Language :: Python :: 3.14
Classifier: Topic :: Text Editors
Requires-Dist: aiopathlib (>=0.6.0,<0.7.0)
Requires-Dist: async-tinydb (>=1.7.3,<2.0.0)
Requires-Dist: asyncer (>=0.0.11,<0.0.12)
Requires-Dist: cyclopts (>=3.24.0,<4.0.0)
Requires-Dist: platformdirs (>=4.5.0,<5.0.0)
Requires-Dist: pydantic-settings (>=2.11.0,<3.0.0)
Requires-Dist: pyperclip (>=1.11.0,<2.0.0)
Requires-Dist: textual-autocomplete (>=4.0.6,<5.0.0)
Requires-Dist: textual-fspicker (>=0.6.0,<0.7.0)
Requires-Dist: textual[syntax] (>=6.0.0,<7.0.0)
Requires-Dist: tomlkit (>=0.13.3,<0.14.0)
Requires-Dist: tree-sitter-agda (>=1.3.3,<2.0.0)
Requires-Dist: tree-sitter-arduino (>=0.24.0,<0.25.0)
Requires-Dist: tree-sitter-bicep (>=1.1.0,<2.0.0)
Requires-Dist: tree-sitter-cpp (>=0.23.4,<0.24.0)
Requires-Dist: tree-sitter-dockerfile (>=0.2.0,<0.3.0)
Requires-Dist: tree-sitter-elixir (>=0.3.4,<0.4.0)
Requires-Dist: tree-sitter-fortran (>=0.5.1,<0.6.0)
Requires-Dist: tree-sitter-glsl (>=0.2.0,<0.3.0)
Requires-Dist: tree-sitter-haskell (>=0.23.1,<0.24.0)
Requires-Dist: tree-sitter-jsdoc (>=0.25.0,<0.26.0)
Requires-Dist: tree-sitter-less (>=1.0.0,<2.0.0)
Requires-Dist: tree-sitter-lua (>=0.2.0,<0.3.0)
Requires-Dist: tree-sitter-luau (>=1.2.0,<2.0.0)
Requires-Dist: tree-sitter-make (>=1.1.1,<2.0.0)
Requires-Dist: tree-sitter-nix (>=0.1.0,<0.2.0)
Requires-Dist: tree-sitter-objc (>=3.0.2,<4.0.0)
Requires-Dist: tree-sitter-requirements (>=0.5.0,<0.6.0)
Requires-Dist: tree-sitter-ruby (>=0.23.1,<0.24.0)
Requires-Dist: tree-sitter-scala (>=0.24.0,<0.25.0)
Requires-Dist: tree-sitter-zig (>=1.1.2,<2.0.0)
Requires-Dist: typing-extensions (>=4.15.0,<5.0.0)
Project-URL: Contributor Guide, https://gole.codeberg.page/gole/contributing
Project-URL: Changelog, https://gole.codeberg.page/gole/changelog/
Project-URL: Documentation, https://gole.codeberg.page/gole
Project-URL: Homepage, https://gole.codeberg.page/gole
Project-URL: Issues, https://codeberg.org/gole/gole/issues
Project-URL: Repository, https://codeberg.org/gole/gole
